README.txt
gameprog.theme-configure.zcml
gameprog.theme.egg-info
setup.cfg
setup.py
setup.pyc
dist/gameprog.theme-0.1-py2.4.egg
dist/gameprog.theme-0.1.tar.gz
dist/gameprog.theme-0.2-py2.4.egg
dist/gameprog.theme-0.2.tar.gz
dist/gameprog.theme-0.3-py2.4.egg
dist/gameprog.theme-0.3.tar.gz
docs/HISTORY.txt
docs/INSTALL.txt
docs/LICENSE.GPL
docs/LICENSE.txt
gameprog/__init__.py
gameprog/__init__.pyc
gameprog.theme.egg-info/PKG-INFO
gameprog.theme.egg-info/SOURCES.txt
gameprog.theme.egg-info/SOURCES.txt.bak
gameprog.theme.egg-info/dependency_links.txt
gameprog.theme.egg-info/entry_points.txt
gameprog.theme.egg-info/namespace_packages.txt
gameprog.theme.egg-info/not-zip-safe
gameprog.theme.egg-info/paster_plugins.txt
gameprog.theme.egg-info/requires.txt
gameprog.theme.egg-info/top_level.txt
gameprog/theme/__init__.py
gameprog/theme/__init__.pyc
gameprog/theme/configure.zcml
gameprog/theme/profiles.zcml
gameprog/theme/setuphandlers.py
gameprog/theme/setuphandlers.pyc
gameprog/theme/skins.zcml
gameprog/theme/tests.py
gameprog/theme/tests.pyc
gameprog/theme/version.txt
gameprog/theme/browser/__init__.py
gameprog/theme/browser/__init__.pyc
gameprog/theme/browser/configure.zcml
gameprog/theme/browser/interfaces.py
gameprog/theme/browser/interfaces.pyc
gameprog/theme/browser/viewlet.pt
gameprog/theme/browser/viewlets.py
gameprog/theme/browser/viewlets.pyc
gameprog/theme/browser/stylesheets/main.css
gameprog/theme/profiles/default/cssregistry.xml
gameprog/theme/profiles/default/gameprog.theme_various.txt
gameprog/theme/profiles/default/import_steps.xml
gameprog/theme/profiles/default/jsregistry.xml
gameprog/theme/profiles/default/skins.xml
gameprog/theme/profiles/default/viewlets.xml
gameprog/theme/skins/gameprog_theme_custom_images/favicon.ico
gameprog/theme/skins/gameprog_theme_custom_images/glogo.jpg
gameprog/theme/skins/gameprog_theme_custom_images/glogo.jpg.bak
gameprog/theme/skins/gameprog_theme_styles/base_properties.props
